package_shreyas/__init__.py
package_shreyas/api_dealer.py
package_shreyas-0.1.dist-info/METADATA
package_shreyas-0.1.dist-info/WHEEL
package_shreyas-0.1.dist-info/top_level.txt
package_shreyas-0.1.dist-info/RECORD
